cso_data/__init__.py
cso_data/cso_grabber.py
cso_data-0.1.3.dist-info/LICENSE.md
cso_data-0.1.3.dist-info/METADATA
cso_data-0.1.3.dist-info/WHEEL
cso_data-0.1.3.dist-info/top_level.txt
cso_data-0.1.3.dist-info/RECORD
